mensajes/__init__.py
mensajes/hola/__init__.py
mensajes/hola/saludos.py
tests/__init__.py
tests/tests_hola.py
Mensajes_m_pome-5.0.dist-info/LICENSE
Mensajes_m_pome-5.0.dist-info/METADATA
Mensajes_m_pome-5.0.dist-info/WHEEL
Mensajes_m_pome-5.0.dist-info/top_level.txt
Mensajes_m_pome-5.0.dist-info/RECORD
