Metadata-Version: 2.1
Name: Mensajes-m-pome
Version: 5.0
Summary: Un paquete para saludar
Home-page: 
Author: Mpome
Author-email: hola@mpome.com
Classifier: Environment :: Console
Classifier: Intended Audience :: Developers
Classifier: License :: OSI Approved :: MIT License
Classifier: Operating System :: OS Independent
Classifier: Programming Language :: Python
Classifier: Programming Language :: Python :: 3.9
Classifier: Programming Language :: Python :: 3.10
Classifier: Topic :: Utilities
License-File: LICENSE
Requires-Dist: numpy (>=1.24.1)
